statmechcrack/__init__.py
statmechcrack/core.py
statmechcrack/isometric.py
statmechcrack/isotensional.py
statmechcrack/mechanical.py
statmechcrack/monte_carlo.py
statmechcrack/utility.py
statmechcrack/q2d/__init__.py
statmechcrack/q2d/core.py
statmechcrack/q2d/isometric.py
statmechcrack/q2d/isotensional.py
statmechcrack/q2d/mechanical.py
statmechcrack/tests/__init__.py
statmechcrack/tests/__main__.py
statmechcrack/tests/test_boundary.py
statmechcrack/tests/test_examples.py
statmechcrack/tests/test_interface.py
statmechcrack/tests/test_many.py
statmechcrack/tests/test_one.py
statmechcrack/tests/test_style.py
statmechcrack/tests/test_zero.py
statmechcrack-0.7.1.dist-info/LICENSE
statmechcrack-0.7.1.dist-info/METADATA
statmechcrack-0.7.1.dist-info/WHEEL
statmechcrack-0.7.1.dist-info/top_level.txt
statmechcrack-0.7.1.dist-info/RECORD
