Metadata-Version: 2.1
Name: statmechcrack
Version: 0.7.1
Summary: Statistical mechanical models for crack growth.
Home-page: https://github.com/sandialabs/statMechCrack
Author: Michael R. Buche, Scott J. Grutzik
Author-email: mrbuche@sandia.gov, sjgrutz@sandia.gov
License: BSD-3-Clause
Project-URL: Anaconda, https://anaconda.org/mrbuche/statmechcrack
Project-URL: Documentation, https://statmechcrack.readthedocs.io/en/latest
Project-URL: GitHub, https://github.com/sandialabs/statmechcrack
Project-URL: Issues, https://github.com/sandialabs/statmechcrack/issues
Keywords: fracture mechanics,statistical mechanics,thermodynamics
Classifier: License :: OSI Approved :: BSD License
Classifier: Development Status :: 5 - Production/Stable
Classifier: Intended Audience :: Science/Research
Classifier: Topic :: Scientific/Engineering
Classifier: Programming Language :: Python
License-File: LICENSE
Requires-Dist: matplotlib
Requires-Dist: numpy
Requires-Dist: scipy
Provides-Extra: all
Requires-Dist: docutils (<0.21,>=0.14) ; extra == 'all'
Requires-Dist: ipykernel ; extra == 'all'
Requires-Dist: ipython ; extra == 'all'
Requires-Dist: jinja2 (>=3.0) ; extra == 'all'
Requires-Dist: nbsphinx ; extra == 'all'
Requires-Dist: pycodestyle ; extra == 'all'
Requires-Dist: pylint ; extra == 'all'
Requires-Dist: pytest ; extra == 'all'
Requires-Dist: pytest-cov ; extra == 'all'
Requires-Dist: sphinx ; extra == 'all'
Requires-Dist: sphinx-copybutton ; extra == 'all'
Requires-Dist: sphinx-rtd-theme ; extra == 'all'
Requires-Dist: sphinxcontrib-bibtex ; extra == 'all'
Provides-Extra: docs
Requires-Dist: docutils (<0.21,>=0.14) ; extra == 'docs'
Requires-Dist: ipykernel ; extra == 'docs'
Requires-Dist: ipython ; extra == 'docs'
Requires-Dist: jinja2 (>=3.0) ; extra == 'docs'
Requires-Dist: nbsphinx ; extra == 'docs'
Requires-Dist: pycodestyle ; extra == 'docs'
Requires-Dist: sphinx ; extra == 'docs'
Requires-Dist: sphinx-copybutton ; extra == 'docs'
Requires-Dist: sphinx-rtd-theme ; extra == 'docs'
Requires-Dist: sphinxcontrib-bibtex ; extra == 'docs'
Provides-Extra: testing
Requires-Dist: pycodestyle ; extra == 'testing'
Requires-Dist: pylint ; extra == 'testing'
Requires-Dist: pytest ; extra == 'testing'
Requires-Dist: pytest-cov ; extra == 'testing'
